pysmash/__init__.py
pysmash/api.py
pysmash/brackets.py
pysmash/exceptions.py
pysmash/smashgg.py
pysmash/tournaments.py
pysmash/utils.py
pysmash-2.1.4.dist-info/DESCRIPTION.rst
pysmash-2.1.4.dist-info/METADATA
pysmash-2.1.4.dist-info/RECORD
pysmash-2.1.4.dist-info/WHEEL
pysmash-2.1.4.dist-info/metadata.json
pysmash-2.1.4.dist-info/top_level.txt
